loop_cgal/_loop_cgal.so
loop_cgal/__init__.py
loop_cgal/utils.py
loop_cgal/bindings.cpp
loop_cgal/.dylibs/libgmpxx.4.dylib
loop_cgal/.dylibs/libgmp.10.dylib
loop_cgal/.dylibs/libmpfr.6.dylib
loop_cgal-0.1.6.dist-info/RECORD
loop_cgal-0.1.6.dist-info/WHEEL
loop_cgal-0.1.6.dist-info/METADATA
