Metadata-Version: 2.2
Name: loop_cgal
Version: 0.1.6
Summary: python bindings for cgal for implicit model meshing
Author-Email: Lachlan Grose <lachlan.grose@monash.edu>
Classifier: Development Status :: 4 - Beta
Classifier: License :: OSI Approved :: MIT License
Classifier: Programming Language :: Python :: 3 :: Only
Classifier: Programming Language :: Python :: 3.7
Classifier: Programming Language :: Python :: 3.8
Classifier: Programming Language :: Python :: 3.9
Classifier: Programming Language :: Python :: 3.10
Classifier: Programming Language :: Python :: 3.11
Classifier: Programming Language :: Python :: 3.12
Requires-Python: >=3.7
Requires-Dist: pyvista
Requires-Dist: vtk
Requires-Dist: scipy
Requires-Dist: numpy
Provides-Extra: test
Requires-Dist: pytest; extra == "test"
